advent_cli/__init__.py
advent_cli/__main__.py
advent_cli/_version.py
advent_cli/cli.py
advent_cli/commands.py
advent_cli/config.py
advent_cli/utils.py
advent_cli-0.2.2.dist-info/LICENSE
advent_cli-0.2.2.dist-info/METADATA
advent_cli-0.2.2.dist-info/WHEEL
advent_cli-0.2.2.dist-info/entry_points.txt
advent_cli-0.2.2.dist-info/top_level.txt
advent_cli-0.2.2.dist-info/RECORD
