Metadata-Version: 2.1
Name: advent-cli
Version: 0.2.2
Summary: Advent of Code command-line interface.
Home-page: https://github.com/fergusch/advent-cli
Author: Christian Ferguson
License: GPLv3
Platform: UNKNOWN
Requires-Python: >=3.7
License-File: LICENSE
Requires-Dist: beautifulsoup4 (>=4.10.0)
Requires-Dist: markdownify (>=0.10.0)
Requires-Dist: pytz (>=2021.1)
Requires-Dist: requests (>=2.26.0)
Requires-Dist: tabulate (>=0.8.9)
Requires-Dist: termcolor (>=1.1.0)
Requires-Dist: windows-curses (>=2.3.0) ; platform_system == "Windows"
Provides-Extra: test
Requires-Dist: freezegun (>=1.1.0) ; extra == 'test'
Requires-Dist: mock (>=4.0.3) ; extra == 'test'
Requires-Dist: pytest (>=6.2.5) ; extra == 'test'
Requires-Dist: pytest-cov (>=3.0.0) ; extra == 'test'
Requires-Dist: pytest-clarity (>=1.0.1) ; extra == 'test'
Requires-Dist: pytest-pycodestyle (>=2.2.0) ; extra == 'test'
